README.rst
setup.py
drakeutil/__init__.py
drakeutil.egg-info/PKG-INFO
drakeutil.egg-info/SOURCES.txt
drakeutil.egg-info/dependency_links.txt
drakeutil.egg-info/requires.txt
drakeutil.egg-info/top_level.txt