Metadata-Version: 1.0
Name: drakeutil
Version: 0.1.0
Summary: Python helpers for the drake workflow language
Home-page: http://bitbucket.org/larsyencken/drakeutil/
Author: Lars Yencken
Author-email: lars@yencken.org
License: ISC
Platform: UNKNOWN
